unipy/__init__.py
unipy/__version__.py
unipy/core/__init__.py
unipy/core/api.py
unipy/dataset/__init__.py
unipy/dataset/api.py
unipy/dataset/resources.tar.gz
unipy/image/__init__.py
unipy/image/api.py
unipy/image/houghmatrix.py
unipy/math/__init__.py
unipy/math/api.py
unipy/math/geometry.py
unipy/plots/__init__.py
unipy/plots/api.py
unipy/plots/boxplot.py
unipy/stats/__init__.py
unipy/stats/api.py
unipy/stats/feature_selection.py
unipy/stats/formula.py
unipy/stats/hypo_test.py
unipy/stats/metrics.py
unipy/tools/__init__.py
unipy/tools/api.py
unipy/tools/data_handler.py
unipy/unipy_test/__init__.py
unipy/unipy_test/test_data_handler.py
unipy/unipy_test/test_dataset.py
unipy/unipy_test/test_example.py
unipy/unipy_test/test_hypothesis.py
unipy/unipy_test/test_samplecode.py
unipy/unipy_test/test_stats.py
unipy/utils/__init__.py
unipy/utils/api.py
unipy/utils/decorator.py
unipy/utils/gdrive.py
unipy/utils/generator.py
unipy/utils/remote_ipyconnector.py
unipy/utils/wrapper.py
unipy-0.1.27.dist-info/METADATA
unipy-0.1.27.dist-info/RECORD
unipy-0.1.27.dist-info/WHEEL
unipy-0.1.27.dist-info/top_level.txt
