Metadata-Version: 2.1
Name: unipy
Version: 0.1.27
Summary: Useful tools for Data Scientists
Home-page: https://unipy.readthedocs.io/en/latest/index.html
Author: Youngju Jaden Kim
Author-email: pydemia@gmail.com
License: MIT License
Download-URL: https://github.com/pydemia/unipy
Platform: UNKNOWN
Classifier: Development Status :: 4 - Beta
Classifier: Environment :: Console
Classifier: Programming Language :: Python :: 3.6
Classifier: Operating System :: OS Independent
Classifier: Intended Audience :: End Users/Desktop
Classifier: Intended Audience :: Developers
Classifier: Intended Audience :: Science/Research
Classifier: Natural Language :: English
Requires-Python: >= 3.6
Requires-Dist: pandas (>=0.20.2)
Requires-Dist: numpy (>=1.13.1)
Requires-Dist: numpydoc (>=0.7.0)
Requires-Dist: scipy (>=0.19.1)
Requires-Dist: scikit-learn (>=0.18.0)
Requires-Dist: statsmodels (>=0.8.0)
Requires-Dist: matplotlib (>=2.0.2)
Requires-Dist: paramiko (>=2.1.2)
Requires-Dist: pandasql (>=0.7.3)
Requires-Dist: seaborn (>=0.8)
Requires-Dist: scikit-image (>=0.13.0)
Requires-Dist: PyDrive (>=1.2.1)
Requires-Dist: oauth2client (>=4.1.2)
Requires-Dist: google-auth-oauthlib (>=0.2.0)
Requires-Dist: pyasn1 (>=0.4.3)
Requires-Dist: pyasn1-modules (>=0.2.1)
Requires-Dist: mglearn (>=0.1.6)
